psypy/__init__.py
psypy/example.py
psypy/psyIP.py
psypy/psySI.py
psypy-0.0.2.dist-info/LICENSE.md
psypy-0.0.2.dist-info/METADATA
psypy-0.0.2.dist-info/WHEEL
psypy-0.0.2.dist-info/top_level.txt
psypy-0.0.2.dist-info/RECORD
