Metadata-Version: 2.1
Name: psypy
Version: 0.0.2
Summary: Python library for calculating psychrometric states of moist air.
Home-page: https://github.com/longapalooza/psypy
Author: Will Long
Author-email: long@latech.edu
License: UNKNOWN
Platform: UNKNOWN
Classifier: Programming Language :: Python :: 3
Classifier: License :: OSI Approved :: MIT License
Classifier: Operating System :: OS Independent
